[{"author":"William Penn","call":"","date":"0428","email":"","himage":"","id":469,"message":"True silence is the rest of the mind; it is to the spirit what sleep is to the body, nourishment and refreshment.","orderBy":468,"timestamp":1714726477881,"title":"Thought of the day","vimage":"https://i.pinimg.com/564x/c0/39/f2/c039f2450644807265df8f0c6dcca6f0.jpg","website":""},{"author":"Immanuel Kant","call":"","date":"0428","email":"","himage":"","id":470,"message":"All our knowledge begins with the senses, proceeds then to the understanding, and ends with reason. There is nothing higher than reason.","orderBy":469,"timestamp":1714726478885,"title":"Thought of the day","vimage":"https://i.pinimg.com/564x/57/41/40/574140fd72f82c9af9889ef6a59df7d3.jpg","website":""},{"author":"Buddha","call":"","date":"0428","email":"","himage":"","id":471,"message":"The thought manifests as the word. The word manifests as the deed. The deed develops into habit. And the habit hardens into character.","orderBy":470,"timestamp":1714726479890,"title":"Thought of the day","vimage":"https://i.pinimg.com/564x/eb/17/41/eb17419cfc7620237bf569e9469d734a.jpg","website":""},{"call":"","date":"0428","email":"","himage":"","id":472,"message":"As the rest of the world is walking out the door, your best friends are the ones walking in.","orderBy":471,"timestamp":1714726480893,"title":"Thought of the day","vimage":"https://i.pinimg.com/564x/b0/cd/6b/b0cd6beb4591332e342ab08e95f94207.jpg","website":""}]