[{"author":"Mother Teresa","call":"","date":"1111","email":"","himage":"","id":1257,"message":"Peace begins with a smile.","orderBy":1256,"timestamp":1714727280466,"title":"Thought of the day","vimage":"https://i.pinimg.com/564x/15/6b/96/156b96cf62460429a737c883913190b0.jpg","website":""},{"author":"Doug Horton","call":"","date":"1111","email":"","himage":"","id":1258,"message":"Be your own hero, it\u0027s cheaper than a movie ticket.","orderBy":1257,"timestamp":1714727281470,"title":"Thought of the day","vimage":"https://i.pinimg.com/564x/22/df/0e/22df0ed6483fbc361437db5787c68173.jpg","website":""},{"author":"Maori proverb","call":"","date":"1111","email":"","himage":"","id":1259,"message":"Turn your face toward the sun and the shadows will fall behind you.","orderBy":1258,"timestamp":1714727282474,"title":"Thought of the day","vimage":"https://i.pinimg.com/564x/07/68/5c/07685c13d7dfe570adc3bec9b029ef9a.jpg","website":""},{"author":"Jack Buck","call":"","date":"1111","email":"","himage":"","id":1260,"message":"Things turn out best for those who make the best of the way things turn out.","orderBy":1259,"timestamp":1714727283478,"title":"Thought of the day","vimage":"https://i.pinimg.com/564x/f2/ec/f6/f2ecf66a208b6aa715fa53308dbd338b.jpg","website":""}]