[{"author":"Abraham Lincoln","call":"","date":"1201","email":"","himage":"","id":1337,"message":"I walk slowly, but I never walk backward.","orderBy":1336,"timestamp":1714727362059,"title":"Thought of the day","vimage":"https://i.pinimg.com/564x/34/1d/83/341d83f23e2cfb88017f7bca218b9306.jpg","website":""},{"author":"Rene Descartes","call":"","date":"1201","email":"","himage":"","id":1338,"message":"Divide each difficulty into as many parts as is feasible and necessary to resolve it.","orderBy":1337,"timestamp":1714727363062,"title":"Thought of the day","vimage":"https://i.pinimg.com/736x/36/ef/42/36ef4255d30260209f9fb6d489108679.jpg","website":""},{"call":"","date":"1201","email":"","himage":"","id":1339,"message":"The best place to find a helping hand is at the end of your own arm.","orderBy":1338,"timestamp":1714727364066,"title":"Thought of the day","vimage":"https://i.pinimg.com/564x/0a/12/9d/0a129d5acca6e0dadfaf9122d865aa8c.jpg","website":""},{"author":"Blaise Pascal","call":"","date":"1201","email":"","himage":"","id":1340,"message":"We know the truth, not only by the reason, but by the heart.","orderBy":1339,"timestamp":1714727365070,"title":"Thought of the day","vimage":"https://i.pinimg.com/564x/d4/ec/8e/d4ec8ed8d9c62313fbfa9a133902dc6f.jpg","website":""}]