[{"author":"Confucius","call":"","date":"1228","email":"","himage":"","id":1445,"message":"Sincerity is the way of Heaven. The attainment of sincerity is the way of men.","orderBy":1444,"timestamp":1714727472220,"title":"Thought of the day","vimage":"https://i.pinimg.com/564x/5c/7e/5e/5c7e5e553847bd5d098e9acab2603b60.jpg","website":""},{"author":"Mohandas Gandhi","call":"","date":"1228","email":"","himage":"","id":1446,"message":"Be the change that you want to see in the world.","orderBy":1445,"timestamp":1714727473224,"title":"Thought of the day","vimage":"https://i.pinimg.com/564x/43/be/50/43be50ab0b181c41a4bca113a7b88d98.jpg","website":""},{"author":"Jim Rohn","call":"","date":"1228","email":"","himage":"","id":1447,"message":"The more you care, the stronger you can be.","orderBy":1446,"timestamp":1714727474227,"title":"Thought of the day","vimage":"https://i.pinimg.com/736x/d2/da/41/d2da41076da2bc5910d750db2593a012.jpg","website":""},{"author":"Oprah Winfrey","call":"","date":"1228","email":"","himage":"","id":1448,"message":"Lots of people want to ride with you in the limo, but what you want is someone who will take the bus with you when the limo breaks down.","orderBy":1447,"timestamp":1714727475231,"title":"Thought of the day","vimage":"https://i.pinimg.com/564x/80/f5/79/80f579089709999aa870eadc2f4197e8.jpg","website":""}]